{
"type": "FeatureCollection",
"name": "Towns",
"features": [
{ "type": "Feature", "properties": { "geoname_id": "3573061", "name": "Saint George", "ascii_name": "Saint George", "alternate_names": [ "Saint George", "Saint George's", "Saint George's Town", "Saint Georges", "Saint George’s", "Saint George’s Town", "Sankta Georgo", "Sent Dzordzas", "Sent Džordžas", "Sent-Dzhordzh", "seinteujojiseu", "sheng qiao zhi si", "snt gwrgs", "snt jwrj  brmwda", "Сент-Джордж", "סנט גורגס", "سنت جورج، برمودا", "سینٹ جارج، برمودا", "სენტ-ჯორჯესი", "セント・ジョージ", "圣乔治斯", "세인트조지스" ], "latitude": "32.38167", "longitude": "-64.67806", "feature_class": "P", "feature_code": "PPL", "country_code": "BM", "admin1_code": "06", "population": 1896, "dem": 16, "timezone": "Atlantic/Bermuda", "modification_date": "2012-01-18", "country": "Bermuda" }, "geometry": { "type": "Point", "coordinates": [ -64.67806, 32.38167 ] } },
{ "type": "Feature", "properties": { "geoname_id": "3573197", "name": "Hamilton", "ascii_name": "Hamilton", "alternate_names": [ "BDA", "Chamilton", "Gamil'tan", "Gamil'ton", "Hamilton", "Hamilton pa Bermuda", "Hamilton på Bermuda", "Hamiltonas", "Hamiltono", "Khamilton", "Khamiltun", "amiltan", "ha mi er dun", "haemilteon", "hamiruton", "hamyltwn", "hemiltana", "hmyltwn", "Χάμιλτον", "Гамильтон", "Гамільтан", "Гамільтон", "Хамилтон", "Хамилтън", "המילטון", "هاميلتون", "همیلتون", "ہیملٹن", "हॅमिल्टन", "ஆமில்டன்", "แฮมิลตัน", "ჰამილტონი", "ハミルトン", "哈密尔顿", "해밀턴" ], "latitude": "32.2949", "longitude": "-64.78303", "feature_class": "P", "feature_code": "PPLC", "country_code": "BM", "admin1_code": "03", "population": 902, "dem": 22, "timezone": "Atlantic/Bermuda", "modification_date": "2019-09-05", "country": "Bermuda" }, "geometry": { "type": "Point", "coordinates": [ -64.78303, 32.2949 ] } }
]
}
